pts_fug_hvpsu/__init__.py
pts_fug_hvpsu/fug_hvpsu.py
pts_fug_hvpsu-0.1.4.dist-info/LICENSE.txt
pts_fug_hvpsu-0.1.4.dist-info/METADATA
pts_fug_hvpsu-0.1.4.dist-info/WHEEL
pts_fug_hvpsu-0.1.4.dist-info/top_level.txt
pts_fug_hvpsu-0.1.4.dist-info/RECORD
