Metadata-Version: 2.1
Name: pts-fug-hvpsu
Version: 0.1.4
Summary: FUG HV PSU Diagnostic Package
Home-page: https://gitlab.com/pass-testing-solutions/fug-power-supply
Author: Pass testing Solutions GmbH
Author-email: shuparna@pass-testing.de
License: MIT
Platform: UNKNOWN
Classifier: License :: OSI Approved :: MIT License
Classifier: Programming Language :: Python :: 3
Classifier: Programming Language :: Python :: 3.9
License-File: LICENSE.txt
